.coveragerc
.gitignore
.travis.yml
CHANGES.rst
CONTRIBUTORS.rst
MANIFEST.in
README.rst
bootstrap.py
buildout.cfg
civicrm-logo.png
configlet.png
contact.png
relations.png
search.png
setup.py
travis.cfg
user.png
docs/LICENSE.GPL
docs/LICENSE.txt
src/collective/__init__.py
src/collective.civicrm.egg-info/PKG-INFO
src/collective.civicrm.egg-info/SOURCES.txt
src/collective.civicrm.egg-info/dependency_links.txt
src/collective.civicrm.egg-info/entry_points.txt
src/collective.civicrm.egg-info/namespace_packages.txt
src/collective.civicrm.egg-info/not-zip-safe
src/collective.civicrm.egg-info/requires.txt
src/collective.civicrm.egg-info/top_level.txt
src/collective/civicrm/__init__.py
src/collective/civicrm/adapters.py
src/collective/civicrm/config.py
src/collective/civicrm/configure.zcml
src/collective/civicrm/controlpanel.py
src/collective/civicrm/interfaces.py
src/collective/civicrm/logger.py
src/collective/civicrm/profiles.zcml
src/collective/civicrm/pythoncivicrm.py
src/collective/civicrm/setuphandlers.py
src/collective/civicrm/testing.py
src/collective/civicrm/timer.py
src/collective/civicrm/userdataschema.py
src/collective/civicrm/browser/__init__.py
src/collective/civicrm/browser/base.py
src/collective/civicrm/browser/configure.zcml
src/collective/civicrm/browser/contact.pt
src/collective/civicrm/browser/contact.py
src/collective/civicrm/browser/find_contacts.pt
src/collective/civicrm/browser/find_contacts.py
src/collective/civicrm/browser/relationships.pt
src/collective/civicrm/browser/relationships.py
src/collective/civicrm/profiles/default/browserlayer.xml
src/collective/civicrm/profiles/default/componentregistry.xml
src/collective/civicrm/profiles/default/controlpanel.xml
src/collective/civicrm/profiles/default/memberdata_properties.xml
src/collective/civicrm/profiles/default/metadata.xml
src/collective/civicrm/profiles/default/propertiestool.xml
src/collective/civicrm/profiles/default/registry.xml
src/collective/civicrm/profiles/uninstall/collective.civicrm.txt
src/collective/civicrm/static/civicrm.png
src/collective/civicrm/static/spinner.gif
src/collective/civicrm/tests/__init__.py
src/collective/civicrm/tests/test_controlpanel.py
src/collective/civicrm/tests/test_example.robot
src/collective/civicrm/tests/test_membership.py
src/collective/civicrm/tests/test_robot.py
src/collective/civicrm/tests/test_setup.py
