Metadata-Version: 1.1
Name: collective.civicrm
Version: 1.0a1
Summary: Plone integration with CiviCRM.
Home-page: https://github.com/collective/collective.civicrm
Author: Simples Consultoria
Author-email: produtos@simplesconsultoria.com.br
License: UNKNOWN
Keywords: civicrm rest api plone
Platform: UNKNOWN
Classifier: Development Status :: 3 - Alpha
Classifier: Environment :: Web Environment
Classifier: Framework :: Plone
Classifier: Framework :: Plone :: 4.2
Classifier: Framework :: Plone :: 4.3
Classifier: Intended Audience :: System Administrators
Classifier: License :: OSI Approved :: GNU General Public License v2 (GPLv2)
Classifier: Operating System :: OS Independent
Classifier: Programming Language :: Python
Classifier: Programming Language :: Python :: 2.7
Classifier: Topic :: Software Development :: Libraries :: Python Modules
